Metadata-Version: 2.1
Name: thetafit
Version: 0.0.1
Summary: Parameter estimation for nonlinear models
Home-page: https://github.com/solbes/thetafit
Author: Antti Solonen
Author-email: antti.solonen@gmail.com
License: MIT
Download-URL: https://github.com/solbes/thetafit/archive/refs/tags/0.0.1.tar.gz
Keywords: bayes,nonlinear,parameter estimation
Platform: UNKNOWN
Classifier: Development Status :: 3 - Alpha
Classifier: Intended Audience :: Science/Research
Classifier: Topic :: Scientific/Engineering :: Artificial Intelligence
Classifier: License :: OSI Approved :: MIT License
Classifier: Programming Language :: Python :: 3
Provides-Extra: dev
